pyfomod/__init__.py
pyfomod/base.py
pyfomod/fomod.py
pyfomod/fomod.xsd
pyfomod/installer.py
pyfomod/parser.py
pyfomod/warnings.py
pyfomod-1.2.1.dist-info/LICENSE
pyfomod-1.2.1.dist-info/WHEEL
pyfomod-1.2.1.dist-info/METADATA
pyfomod-1.2.1.dist-info/RECORD
