Metadata-Version: 2.1
Name: pyfomod
Version: 1.2.1
Summary: A high-level fomod library written in Python.
Home-page: https://github.com/GandaG/pyfomod
License: Apache-2.0
Author: Daniel Nunes
Author-email: daniel.henri.nunes@gmail.com
Requires-Python: >=3.6,<4.0
Classifier: Intended Audience :: Developers
Classifier: License :: OSI Approved :: Apache Software License
Classifier: Programming Language :: Python :: 3
Classifier: Programming Language :: Python :: 3.6
Classifier: Programming Language :: Python :: 3.7
Classifier: Topic :: Software Development :: Libraries
Requires-Dist: lxml (>=4,<5)
Project-URL: Documentation, https://pyfomod.rtfd.io/
Project-URL: Repository, https://github.com/GandaG/pyfomod
